pyfvm/__init__.py
pyfvm/_license_validation.py
pyfvm/discretize.py
pyfvm/discretize_linear.py
pyfvm/form_language.py
pyfvm/fvm_matrix.py
pyfvm/fvm_problem.py
pyfvm/jacobian.py
pyfvm/linear_fvm_problem.py
pyfvm/nonlinear_methods.py
pyfvm-0.4.8.dist-info/METADATA
pyfvm-0.4.8.dist-info/WHEEL
pyfvm-0.4.8.dist-info/top_level.txt
pyfvm-0.4.8.dist-info/RECORD
