Metadata-Version: 2.1
Name: pyfvm
Version: 0.4.8
Summary: Finite volume discretizations for Python
Author-email: Nico Schlömer <nico.schloemer@gmail.com>
Project-URL: Home, https://github.com/meshpro/pyfvm
Project-URL: Issues, https://github.com/meshpro/pyfvm/issues
Classifier: Development Status :: 5 - Production/Stable
Classifier: Intended Audience :: Science/Research
Classifier: License :: Other/Proprietary License
Classifier: Operating System :: OS Independent
Classifier: Programming Language :: Python
Classifier: Programming Language :: Python :: 3
Classifier: Programming Language :: Python :: 3.9
Classifier: Programming Language :: Python :: 3.10
Classifier: Programming Language :: Python :: 3.11
Classifier: Programming Language :: Python :: 3.12
Classifier: Programming Language :: Python :: 3.13
Classifier: Topic :: Scientific/Engineering
Classifier: Topic :: Scientific/Engineering :: Mathematics
Requires-Python: >=3.9
Requires-Dist: x21 (>=0.5.3)
Requires-Dist: meshplex<0.20.0,>=0.18.0
Requires-Dist: npx
Requires-Dist: numpy
Requires-Dist: scipy
Requires-Dist: sphinxcontrib-bibtex
Requires-Dist: sympy
